{
    "ID_Frame": 3,
    "People": [
        {
            "face_rotation": {
                "pitch": 0.0,
                "roll": 0.0,
                "yaw": 0.0
            },
            "personID": 0,
            "skeleton": [
                {
                    "pointID": 0,
                    "x": 0.990156352519989,
                    "y": 0.17897987365722656,
                    "z": 2.4839999675750732,
                    "confidence": 0.8553594350814819
                },
                {
                    "pointID": 1,
                    "x": 1.163408875465393,
                    "y": 0.35641947388648987,
                    "z": 3.500999927520752,
                    "confidence": 0.7264700531959534
                },
                {
                    "pointID": 2,
                    "x": 0.9069930911064148,
                    "y": 0.25078749656677246,
                    "z": 2.5209999084472656,
                    "confidence": 0.7537453174591064
                },
                {
                    "pointID": 3,
                    "x": 0.855415940284729,
                    "y": 0.034891847521066666,
                    "z": 2.3480000495910645,
                    "confidence": 0.7742161750793457
                },
                {
                    "pointID": 4,
                    "x": 0.949812650680542,
                    "y": -0.05035450682044029,
                    "z": 2.315999984741211,
                    "confidence": 0.7436623573303223
                },
                {
                    "pointID": 5,
                    "x": 1.0861831903457642,
                    "y": 0.37650564312934875,
                    "z": 3.5369999408721924,
                    "confidence": 0.5633255243301392
                },
                {
                    "pointID": 6,
                    "x": 0.7689281105995178,
                    "y": 0.0028239854145795107,
                    "z": 2.430999994277954,
                    "confidence": 0.1419745683670044
                },
                {
                    "pointID": 7,
                    "x": 0.8853225111961365,
                    "y": -0.060434386134147644,
                    "z": 2.299999952316284,
                    "confidence": 0.2195114940404892
                },
                {
                    "pointID": 8,
                    "x": 0.6521196961402893,
                    "y": -0.18646949529647827,
                    "z": 2.430999994277954,
                    "confidence": 0.6176295876502991
                },
                {
                    "pointID": 9,
                    "x": 0.6928543448448181,
                    "y": -0.19882820546627045,
                    "z": 2.380000114440918,
                    "confidence": 0.5805529952049255
                },
                {
                    "pointID": 10,
                    "x": 0.7425771355628967,
                    "y": -0.5292337536811829,
                    "z": 2.3480000495910645,
                    "confidence": 0.5009888410568237
                },
                {
                    "pointID": 11,
                    "x": 0.7112657427787781,
                    "y": -0.8241757750511169,
                    "z": 2.315999984741211,
                    "confidence": 0.2794429361820221
                },
                {
                    "pointID": 12,
                    "x": 0.612727701663971,
                    "y": -0.1816609501838684,
                    "z": 2.5209999084472656,
                    "confidence": 0.5661603808403015
                },
                {
                    "pointID": 13,
                    "x": 0.6655568480491638,
                    "y": -0.4711131155490875,
                    "z": 2.380000114440918,
                    "confidence": 0.28377479314804077
                },
                {
                    "pointID": 14,
                    "x": 0.6673942804336548,
                    "y": -0.8086140155792236,
                    "z": 2.3480000495910645,
                    "confidence": 0.06828134506940842
                },
                {
                    "pointID": 15,
                    "x": 1.0633442401885986,
                    "y": 0.226129949092865,
                    "z": 2.63700008392334,
                    "confidence": 0.904185950756073
                },
                {
                    "pointID": 16,
                    "x": -0.0,
                    "y": 0.0,
                    "z": 0.0,
                    "confidence": 0.0
                },
                {
                    "pointID": 17,
                    "x": 1.0272107124328613,
                    "y": 0.2928158938884735,
                    "z": 2.63700008392334,
                    "confidence": 0.7853378057479858
                },
                {
                    "pointID": 18,
                    "x": -0.0,
                    "y": 0.0,
                    "z": 0.0,
                    "confidence": 0.0
                },
                {
                    "pointID": 19,
                    "x": -0.0,
                    "y": 0.0,
                    "z": 0.0,
                    "confidence": 0.0
                },
                {
                    "pointID": 20,
                    "x": -0.0,
                    "y": 0.0,
                    "z": 0.0,
                    "confidence": 0.0
                },
                {
                    "pointID": 21,
                    "x": -0.0,
                    "y": 0.0,
                    "z": 0.0,
                    "confidence": 0.0
                },
                {
                    "pointID": 22,
                    "x": 0.7962760925292969,
                    "y": -0.8566380739212036,
                    "z": 2.3320000171661377,
                    "confidence": 0.14028480648994446
                },
                {
                    "pointID": 23,
                    "x": 0.7590246200561523,
                    "y": -0.8612067103385925,
                    "z": 2.315999984741211,
                    "confidence": 0.12385884672403336
                },
                {
                    "pointID": 24,
                    "x": 0.6948772072792053,
                    "y": -0.8512527942657471,
                    "z": 2.3320000171661377,
                    "confidence": 0.17972035706043243
                }
            ]
        }
    ],
    "thingId": "digitaltwin:Casa_Sala_Pranzo:1"
}