{
    "ID_Frame": 136,
    "People": [
        {
            "face_rotation": {
                "pitch": 0.0,
                "yaw": 0.0,
                "roll": 0.0
            },
            "personID": 0,
            "skeleton": [
                {
                    "pointID": 0,
                    "x": 0.5015745162963867,
                    "y": -0.07356669753789902,
                    "z": 3.2700002193450928,
                    "confidence": 0.8373380899429321
                },
                {
                    "pointID": 1,
                    "x": 0.6467372179031372,
                    "y": -0.14822176098823547,
                    "z": 3.005000114440918,
                    "confidence": 0.8047038316726685
                },
                {
                    "pointID": 2,
                    "x": 0.5730312466621399,
                    "y": -0.1496376097202301,
                    "z": 3.0380001068115234,
                    "confidence": 0.8238559365272522
                },
                {
                    "pointID": 3,
                    "x": 0.5432119965553284,
                    "y": -0.5207189321517944,
                    "z": 3.014000177383423,
                    "confidence": 0.19335193932056427
                },
                {
                    "pointID": 4,
                    "x": -0.0,
                    "y": 0.0,
                    "z": 0.0,
                    "confidence": 0.0
                },
                {
                    "pointID": 5,
                    "x": 0.708417534828186,
                    "y": -0.1699022650718689,
                    "z": 2.936000108718872,
                    "confidence": 0.8981572389602661
                },
                {
                    "pointID": 6,
                    "x": 0.7155352830886841,
                    "y": -0.4946272075176239,
                    "z": 2.8590002059936523,
                    "confidence": 0.9336423277854919
                },
                {
                    "pointID": 7,
                    "x": 0.700442910194397,
                    "y": -0.7339306473731995,
                    "z": 2.8990001678466797,
                    "confidence": 0.9540184736251831
                },
                {
                    "pointID": 8,
                    "x": 0.5676783323287964,
                    "y": -0.7346929907798767,
                    "z": 3.008000135421753,
                    "confidence": 0.8924529552459717
                },
                {
                    "pointID": 9,
                    "x": 0.541917622089386,
                    "y": -0.7370336651802063,
                    "z": 3.0180001258850098,
                    "confidence": 0.9228841662406921
                },
                {
                    "pointID": 10,
                    "x": 0.6154583692550659,
                    "y": -1.2289031744003296,
                    "z": 3.26200008392334,
                    "confidence": 0.8674312829971313
                },
                {
                    "pointID": 11,
                    "x": 0.6843459010124207,
                    "y": -1.543403148651123,
                    "z": 3.31600022315979,
                    "confidence": 0.8585906028747559
                },
                {
                    "pointID": 12,
                    "x": 0.6199606657028198,
                    "y": -0.7264726161956787,
                    "z": 2.878000020980835,
                    "confidence": 0.8791264891624451
                },
                {
                    "pointID": 13,
                    "x": 0.7550485134124756,
                    "y": -1.1756423711776733,
                    "z": 3.120000123977661,
                    "confidence": 0.9090307950973511
                },
                {
                    "pointID": 14,
                    "x": 0.8078197240829468,
                    "y": -1.5274014472961426,
                    "z": 3.2190001010894775,
                    "confidence": 0.8213987350463867
                },
                {
                    "pointID": 15,
                    "x": -0.0,
                    "y": 0.0,
                    "z": 0.0,
                    "confidence": 0.0
                },
                {
                    "pointID": 16,
                    "x": 0.4994608163833618,
                    "y": -0.014266117475926876,
                    "z": 3.082000255584717,
                    "confidence": 0.8300012350082397
                },
                {
                    "pointID": 17,
                    "x": -0.0,
                    "y": 0.0,
                    "z": 0.0,
                    "confidence": 0.0
                },
                {
                    "pointID": 18,
                    "x": 0.5529773235321045,
                    "y": 0.03977113217115402,
                    "z": 3.077000141143799,
                    "confidence": 0.8978579044342041
                },
                {
                    "pointID": 19,
                    "x": 0.7459772229194641,
                    "y": -1.5802843570709229,
                    "z": 3.330000162124634,
                    "confidence": 0.5323973894119263
                },
                {
                    "pointID": 20,
                    "x": 0.7707509398460388,
                    "y": -1.6764836311340332,
                    "z": 3.075000047683716,
                    "confidence": 0.5597370266914368
                },
                {
                    "pointID": 21,
                    "x": 0.8003949522972107,
                    "y": -1.5406721830368042,
                    "z": 3.188000202178955,
                    "confidence": 0.6823029518127441
                },
                {
                    "pointID": 22,
                    "x": 0.5664364099502563,
                    "y": -1.569211483001709,
                    "z": 3.309000253677368,
                    "confidence": 0.6390701532363892
                },
                {
                    "pointID": 23,
                    "x": 0.5669886469841003,
                    "y": -1.5453580617904663,
                    "z": 3.318000078201294,
                    "confidence": 0.6479528546333313
                },
                {
                    "pointID": 24,
                    "x": 0.7462273836135864,
                    "y": -1.5803792476654053,
                    "z": 3.330000162124634,
                    "confidence": 0.6127540469169617
                }
            ]
        }
    ],
    "thingId": "digitaltwin:Laboratorio_Corridoio:1",
    "Has_Fallen": false
}