{
    "ID_Frame": 665,
    "People": [
        {
            "face_rotation": {
                "pitch": 0.0,
                "yaw": 0.0,
                "roll": 0.0
            },
            "personID": 0,
            "skeleton": [
                {
                    "pointID": 0,
                    "x": -0.13577528297901154,
                    "y": -0.46361854672431946,
                    "z": 1.2010000944137573,
                    "confidence": 0.9450044631958008
                },
                {
                    "pointID": 1,
                    "x": 0.025314051657915115,
                    "y": -0.6105185747146606,
                    "z": 1.2630000114440918,
                    "confidence": 0.7554383277893066
                },
                {
                    "pointID": 2,
                    "x": -0.14006564021110535,
                    "y": -0.6157668232917786,
                    "z": 1.349000096321106,
                    "confidence": 0.8242824077606201
                },
                {
                    "pointID": 3,
                    "x": -0.23957625031471252,
                    "y": -0.7476692795753479,
                    "z": 1.371000051498413,
                    "confidence": 0.3276951014995575
                },
                {
                    "pointID": 4,
                    "x": -0.25225937366485596,
                    "y": -0.749224066734314,
                    "z": 1.374000072479248,
                    "confidence": 0.055565301328897476
                },
                {
                    "pointID": 5,
                    "x": 0.1427747905254364,
                    "y": -0.6598070859909058,
                    "z": 1.2100000381469727,
                    "confidence": 0.7017764449119568
                },
                {
                    "pointID": 6,
                    "x": -0.0,
                    "y": 0.0,
                    "z": 0.0,
                    "confidence": 0.0
                },
                {
                    "pointID": 7,
                    "x": -0.0,
                    "y": 0.0,
                    "z": 0.0,
                    "confidence": 0.0
                },
                {
                    "pointID": 8,
                    "x": -0.0,
                    "y": 0.0,
                    "z": 0.0,
                    "confidence": 0.0
                },
                {
                    "pointID": 9,
                    "x": -0.0,
                    "y": 0.0,
                    "z": 0.0,
                    "confidence": 0.0
                },
                {
                    "pointID": 10,
                    "x": -0.0,
                    "y": 0.0,
                    "z": 0.0,
                    "confidence": 0.0
                },
                {
                    "pointID": 11,
                    "x": -0.0,
                    "y": 0.0,
                    "z": 0.0,
                    "confidence": 0.0
                },
                {
                    "pointID": 12,
                    "x": -0.0,
                    "y": 0.0,
                    "z": 0.0,
                    "confidence": 0.0
                },
                {
                    "pointID": 13,
                    "x": -0.0,
                    "y": 0.0,
                    "z": 0.0,
                    "confidence": 0.0
                },
                {
                    "pointID": 14,
                    "x": -0.0,
                    "y": 0.0,
                    "z": 0.0,
                    "confidence": 0.0
                },
                {
                    "pointID": 15,
                    "x": -0.14695732295513153,
                    "y": -0.4133330285549164,
                    "z": 1.2100000381469727,
                    "confidence": 0.29593008756637573
                },
                {
                    "pointID": 16,
                    "x": -0.1229720264673233,
                    "y": -0.44771283864974976,
                    "z": 1.1890000104904175,
                    "confidence": 0.898112952709198
                },
                {
                    "pointID": 17,
                    "x": -0.0,
                    "y": 0.0,
                    "z": 0.0,
                    "confidence": 0.0
                },
                {
                    "pointID": 18,
                    "x": 0.003224715357646346,
                    "y": -0.4464947581291199,
                    "z": 1.2130000591278076,
                    "confidence": 0.8517940640449524
                },
                {
                    "pointID": 19,
                    "x": -0.0,
                    "y": 0.0,
                    "z": 0.0,
                    "confidence": 0.0
                },
                {
                    "pointID": 20,
                    "x": -0.0,
                    "y": 0.0,
                    "z": 0.0,
                    "confidence": 0.0
                },
                {
                    "pointID": 21,
                    "x": -0.0,
                    "y": 0.0,
                    "z": 0.0,
                    "confidence": 0.0
                },
                {
                    "pointID": 22,
                    "x": -0.0,
                    "y": 0.0,
                    "z": 0.0,
                    "confidence": 0.0
                },
                {
                    "pointID": 23,
                    "x": -0.0,
                    "y": 0.0,
                    "z": 0.0,
                    "confidence": 0.0
                },
                {
                    "pointID": 24,
                    "x": -0.0,
                    "y": 0.0,
                    "z": 0.0,
                    "confidence": 0.0
                }
            ]
        }
    ],
    "thingId": "digitaltwin:Laboratorio_Corridoio:1",
    "Has_Fallen": false
}