{
    "ID_Frame": 629,
    "People": [
        {
            "face_rotation": {
                "pitch": -23.01725404141805,
                "yaw": -35.67049353491918,
                "roll": -8.199485881432944
            },
            "personID": 0,
            "skeleton": [
                {
                    "pointID": 0,
                    "x": 0.3479948341846466,
                    "y": 0.0062474715523421764,
                    "z": 1.4950001239776611,
                    "confidence": 0.8742859363555908
                },
                {
                    "pointID": 1,
                    "x": 0.48587900400161743,
                    "y": -0.1176646277308464,
                    "z": 1.5560001134872437,
                    "confidence": 0.8822845220565796
                },
                {
                    "pointID": 2,
                    "x": 0.30129262804985046,
                    "y": -0.11157961934804916,
                    "z": 1.6710001230239868,
                    "confidence": 0.876459002494812
                },
                {
                    "pointID": 3,
                    "x": 0.20887789130210876,
                    "y": -0.32379335165023804,
                    "z": 1.7760001420974731,
                    "confidence": 0.9277656674385071
                },
                {
                    "pointID": 4,
                    "x": 0.2727417051792145,
                    "y": -0.4032071828842163,
                    "z": 1.5940001010894775,
                    "confidence": 0.9960760474205017
                },
                {
                    "pointID": 5,
                    "x": 0.62262362241745,
                    "y": -0.11698434501886368,
                    "z": 1.5510001182556152,
                    "confidence": 0.8736917972564697
                },
                {
                    "pointID": 6,
                    "x": 0.7527375221252441,
                    "y": -0.3536268472671509,
                    "z": 1.565000057220459,
                    "confidence": 0.8656306862831116
                },
                {
                    "pointID": 7,
                    "x": 0.5657855868339539,
                    "y": -0.38089191913604736,
                    "z": 1.409000039100647,
                    "confidence": 0.8503559231758118
                },
                {
                    "pointID": 8,
                    "x": 0.4744747281074524,
                    "y": -0.6856889128684998,
                    "z": 1.5630000829696655,
                    "confidence": 0.8217794299125671
                },
                {
                    "pointID": 9,
                    "x": 0.3625102639198303,
                    "y": -0.6814391016960144,
                    "z": 1.6180000305175781,
                    "confidence": 0.785841703414917
                },
                {
                    "pointID": 10,
                    "x": 0.34654685854911804,
                    "y": -0.9158602356910706,
                    "z": 1.6790001392364502,
                    "confidence": 0.08527088910341263
                },
                {
                    "pointID": 11,
                    "x": -0.0,
                    "y": 0.0,
                    "z": 0.0,
                    "confidence": 0.0
                },
                {
                    "pointID": 12,
                    "x": 0.5902081727981567,
                    "y": -0.704634964466095,
                    "z": 1.5750000476837158,
                    "confidence": 0.81413733959198
                },
                {
                    "pointID": 13,
                    "x": -0.0,
                    "y": 0.0,
                    "z": 0.0,
                    "confidence": 0.0
                },
                {
                    "pointID": 14,
                    "x": -0.0,
                    "y": 0.0,
                    "z": 0.0,
                    "confidence": 0.0
                },
                {
                    "pointID": 15,
                    "x": 0.3202430009841919,
                    "y": 0.04568348824977875,
                    "z": 1.4890000820159912,
                    "confidence": 0.8733229637145996
                },
                {
                    "pointID": 16,
                    "x": 0.35539713501930237,
                    "y": 0.04506916180253029,
                    "z": 1.468000054359436,
                    "confidence": 1.0021003484725952
                },
                {
                    "pointID": 17,
                    "x": -0.0,
                    "y": 0.0,
                    "z": 0.0,
                    "confidence": 0.0
                },
                {
                    "pointID": 18,
                    "x": 0.4703442454338074,
                    "y": 0.05967853218317032,
                    "z": 1.5040000677108765,
                    "confidence": 0.9793462157249451
                },
                {
                    "pointID": 19,
                    "x": -0.0,
                    "y": 0.0,
                    "z": 0.0,
                    "confidence": 0.0
                },
                {
                    "pointID": 20,
                    "x": -0.0,
                    "y": 0.0,
                    "z": 0.0,
                    "confidence": 0.0
                },
                {
                    "pointID": 21,
                    "x": -0.0,
                    "y": 0.0,
                    "z": 0.0,
                    "confidence": 0.0
                },
                {
                    "pointID": 22,
                    "x": -0.0,
                    "y": 0.0,
                    "z": 0.0,
                    "confidence": 0.0
                },
                {
                    "pointID": 23,
                    "x": -0.0,
                    "y": 0.0,
                    "z": 0.0,
                    "confidence": 0.0
                },
                {
                    "pointID": 24,
                    "x": -0.0,
                    "y": 0.0,
                    "z": 0.0,
                    "confidence": 0.0
                }
            ]
        }
    ],
    "thingId": "digitaltwin:Laboratorio_Corridoio:1",
    "Has_Fallen": false
}