{
    "ID_Frame": 158,
    "People": [
        {
            "face_rotation": {
                "pitch": -24.8743255513756,
                "yaw": -23.49679800055802,
                "roll": -5.516683156257803
            },
            "personID": 0,
            "skeleton": [
                {
                    "pointID": 0,
                    "x": -0.1642046719789505,
                    "y": -0.7378203868865967,
                    "z": 1.3530000448226929,
                    "confidence": 0.9612001776695251
                },
                {
                    "pointID": 1,
                    "x": -0.09693943709135056,
                    "y": -0.7743908762931824,
                    "z": 1.4200000762939453,
                    "confidence": 0.8128124475479126
                },
                {
                    "pointID": 2,
                    "x": -0.27244168519973755,
                    "y": -0.8102495074272156,
                    "z": 1.4860000610351562,
                    "confidence": 0.6603024005889893
                },
                {
                    "pointID": 3,
                    "x": -0.2729035019874573,
                    "y": -0.8105185627937317,
                    "z": 1.4860000610351562,
                    "confidence": 0.19203317165374756
                },
                {
                    "pointID": 4,
                    "x": -0.0,
                    "y": 0.0,
                    "z": 0.0,
                    "confidence": 0.0
                },
                {
                    "pointID": 5,
                    "x": 0.055616941303014755,
                    "y": -0.7989323139190674,
                    "z": 1.465000033378601,
                    "confidence": 0.5976481437683105
                },
                {
                    "pointID": 6,
                    "x": 0.1495215892791748,
                    "y": -0.8139644861221313,
                    "z": 1.4920001029968262,
                    "confidence": 0.12645359337329865
                },
                {
                    "pointID": 7,
                    "x": -0.0,
                    "y": 0.0,
                    "z": 0.0,
                    "confidence": 0.0
                },
                {
                    "pointID": 8,
                    "x": -0.0,
                    "y": 0.0,
                    "z": 0.0,
                    "confidence": 0.0
                },
                {
                    "pointID": 9,
                    "x": -0.0,
                    "y": 0.0,
                    "z": 0.0,
                    "confidence": 0.0
                },
                {
                    "pointID": 10,
                    "x": -0.0,
                    "y": 0.0,
                    "z": 0.0,
                    "confidence": 0.0
                },
                {
                    "pointID": 11,
                    "x": -0.0,
                    "y": 0.0,
                    "z": 0.0,
                    "confidence": 0.0
                },
                {
                    "pointID": 12,
                    "x": -0.0,
                    "y": 0.0,
                    "z": 0.0,
                    "confidence": 0.0
                },
                {
                    "pointID": 13,
                    "x": -0.0,
                    "y": 0.0,
                    "z": 0.0,
                    "confidence": 0.0
                },
                {
                    "pointID": 14,
                    "x": -0.0,
                    "y": 0.0,
                    "z": 0.0,
                    "confidence": 0.0
                },
                {
                    "pointID": 15,
                    "x": -0.21156656742095947,
                    "y": -0.6643363237380981,
                    "z": 1.350000023841858,
                    "confidence": 0.7711375951766968
                },
                {
                    "pointID": 16,
                    "x": -0.14028212428092957,
                    "y": -0.7381914854049683,
                    "z": 1.3540000915527344,
                    "confidence": 0.8649296760559082
                },
                {
                    "pointID": 17,
                    "x": -0.0,
                    "y": 0.0,
                    "z": 0.0,
                    "confidence": 0.0
                },
                {
                    "pointID": 18,
                    "x": -0.046906545758247375,
                    "y": -0.6626081466674805,
                    "z": 1.4240000247955322,
                    "confidence": 0.9214728474617004
                },
                {
                    "pointID": 19,
                    "x": -0.0,
                    "y": 0.0,
                    "z": 0.0,
                    "confidence": 0.0
                },
                {
                    "pointID": 20,
                    "x": -0.0,
                    "y": 0.0,
                    "z": 0.0,
                    "confidence": 0.0
                },
                {
                    "pointID": 21,
                    "x": -0.0,
                    "y": 0.0,
                    "z": 0.0,
                    "confidence": 0.0
                },
                {
                    "pointID": 22,
                    "x": -0.0,
                    "y": 0.0,
                    "z": 0.0,
                    "confidence": 0.0
                },
                {
                    "pointID": 23,
                    "x": -0.0,
                    "y": 0.0,
                    "z": 0.0,
                    "confidence": 0.0
                },
                {
                    "pointID": 24,
                    "x": -0.0,
                    "y": 0.0,
                    "z": 0.0,
                    "confidence": 0.0
                }
            ]
        }
    ],
    "thingId": "digitaltwin:Laboratorio_Corridoio:1",
    "Has_Fallen": false
}