{
    "ID_Frame": 109,
    "People": [
        {
            "face_rotation": {
                "pitch": 0.0,
                "yaw": 0.0,
                "roll": 0.0
            },
            "personID": 0,
            "skeleton": [
                {
                    "pointID": 0,
                    "x": 0.5760068297386169,
                    "y": 0.07033753395080566,
                    "z": 3.198000192642212,
                    "confidence": 0.9072024822235107
                },
                {
                    "pointID": 1,
                    "x": 0.6608877778053284,
                    "y": -0.135789155960083,
                    "z": 3.3430001735687256,
                    "confidence": 0.9070506691932678
                },
                {
                    "pointID": 2,
                    "x": 0.5340112447738647,
                    "y": -0.13307635486125946,
                    "z": 3.2980000972747803,
                    "confidence": 0.9156747460365295
                },
                {
                    "pointID": 3,
                    "x": 0.9430803656578064,
                    "y": -0.884978711605072,
                    "z": 8.67300033569336,
                    "confidence": 0.9610921144485474
                },
                {
                    "pointID": 4,
                    "x": 0.4314735531806946,
                    "y": -0.07117310166358948,
                    "z": 3.180000066757202,
                    "confidence": 0.7883678674697876
                },
                {
                    "pointID": 5,
                    "x": 0.855785071849823,
                    "y": -0.16197137534618378,
                    "z": 3.2990002632141113,
                    "confidence": 0.9039516448974609
                },
                {
                    "pointID": 6,
                    "x": 0.9936568737030029,
                    "y": -0.5079158544540405,
                    "z": 3.2720000743865967,
                    "confidence": 0.8571286201477051
                },
                {
                    "pointID": 7,
                    "x": 0.9568765759468079,
                    "y": -0.74091637134552,
                    "z": 3.1500000953674316,
                    "confidence": 0.9341331124305725
                },
                {
                    "pointID": 8,
                    "x": 0.6299945712089539,
                    "y": -0.7769767642021179,
                    "z": 3.188000202178955,
                    "confidence": 0.9169520139694214
                },
                {
                    "pointID": 9,
                    "x": 0.5533769726753235,
                    "y": -0.7880212068557739,
                    "z": 3.2350001335144043,
                    "confidence": 0.9765397310256958
                },
                {
                    "pointID": 10,
                    "x": 0.592563271522522,
                    "y": -1.1566578149795532,
                    "z": 3.302000045776367,
                    "confidence": 0.9011576175689697
                },
                {
                    "pointID": 11,
                    "x": 0.670595645904541,
                    "y": -1.5926405191421509,
                    "z": 3.557000160217285,
                    "confidence": 0.8732593059539795
                },
                {
                    "pointID": 12,
                    "x": 0.7607086300849915,
                    "y": -0.7667495608329773,
                    "z": 3.1440000534057617,
                    "confidence": 0.9923416376113892
                },
                {
                    "pointID": 13,
                    "x": 0.7910287380218506,
                    "y": -1.2033511400222778,
                    "z": 3.2720000743865967,
                    "confidence": 0.899150013923645
                },
                {
                    "pointID": 14,
                    "x": 0.7915531992912292,
                    "y": -1.5258539915084839,
                    "z": 3.2780001163482666,
                    "confidence": 0.8597133755683899
                },
                {
                    "pointID": 15,
                    "x": 0.5739127993583679,
                    "y": 0.09871242940425873,
                    "z": 3.19700026512146,
                    "confidence": 0.9229127764701843
                },
                {
                    "pointID": 16,
                    "x": 0.6009448170661926,
                    "y": 0.09798502177000046,
                    "z": 3.180000066757202,
                    "confidence": 0.9154070019721985
                },
                {
                    "pointID": 17,
                    "x": 0.5499125123023987,
                    "y": 0.09742679446935654,
                    "z": 3.2180001735687256,
                    "confidence": 0.3294592499732971
                },
                {
                    "pointID": 18,
                    "x": 1.7539305686950684,
                    "y": 0.16587087512016296,
                    "z": 7.527000427246094,
                    "confidence": 0.8357774019241333
                },
                {
                    "pointID": 19,
                    "x": 0.6807644963264465,
                    "y": -1.535701870918274,
                    "z": 3.2970001697540283,
                    "confidence": 0.6175448894500732
                },
                {
                    "pointID": 20,
                    "x": 0.790463387966156,
                    "y": -1.5522308349609375,
                    "z": 3.2720000743865967,
                    "confidence": 0.6290135383605957
                },
                {
                    "pointID": 21,
                    "x": 0.7913808226585388,
                    "y": -1.5272512435913086,
                    "z": 3.2780001163482666,
                    "confidence": 0.7044129967689514
                },
                {
                    "pointID": 22,
                    "x": 0.6062282919883728,
                    "y": -1.648738145828247,
                    "z": 3.5430002212524414,
                    "confidence": 0.764354407787323
                },
                {
                    "pointID": 23,
                    "x": 0.577003538608551,
                    "y": -1.6542370319366455,
                    "z": 3.558000087738037,
                    "confidence": 0.7372304797172546
                },
                {
                    "pointID": 24,
                    "x": 0.6640264987945557,
                    "y": -1.6042373180389404,
                    "z": 3.516000270843506,
                    "confidence": 0.7369107604026794
                }
            ]
        }
    ],
    "thingId": "digitaltwin:Laboratorio_Corridoio:1",
    "Has_Fallen": false
}