{
    "ID_Frame": 266,
    "People": [
        {
            "face_rotation": {
                "pitch": -25.220733536589403,
                "yaw": -12.051993077861995,
                "roll": -10.502957902963617
            },
            "personID": 0,
            "skeleton": [
                {
                    "pointID": 0,
                    "x": 0.01606369949877262,
                    "y": -0.7654222249984741,
                    "z": 1.4040000438690186,
                    "confidence": 0.8074013590812683
                },
                {
                    "pointID": 1,
                    "x": -0.0,
                    "y": 0.0,
                    "z": 0.0,
                    "confidence": 0.0
                },
                {
                    "pointID": 2,
                    "x": -0.0,
                    "y": 0.0,
                    "z": 0.0,
                    "confidence": 0.0
                },
                {
                    "pointID": 3,
                    "x": -0.0,
                    "y": 0.0,
                    "z": 0.0,
                    "confidence": 0.0
                },
                {
                    "pointID": 4,
                    "x": -0.0,
                    "y": 0.0,
                    "z": 0.0,
                    "confidence": 0.0
                },
                {
                    "pointID": 5,
                    "x": -0.0,
                    "y": 0.0,
                    "z": 0.0,
                    "confidence": 0.0
                },
                {
                    "pointID": 6,
                    "x": -0.0,
                    "y": 0.0,
                    "z": 0.0,
                    "confidence": 0.0
                },
                {
                    "pointID": 7,
                    "x": -0.0,
                    "y": 0.0,
                    "z": 0.0,
                    "confidence": 0.0
                },
                {
                    "pointID": 8,
                    "x": -0.0,
                    "y": 0.0,
                    "z": 0.0,
                    "confidence": 0.0
                },
                {
                    "pointID": 9,
                    "x": -0.0,
                    "y": 0.0,
                    "z": 0.0,
                    "confidence": 0.0
                },
                {
                    "pointID": 10,
                    "x": -0.0,
                    "y": 0.0,
                    "z": 0.0,
                    "confidence": 0.0
                },
                {
                    "pointID": 11,
                    "x": -0.0,
                    "y": 0.0,
                    "z": 0.0,
                    "confidence": 0.0
                },
                {
                    "pointID": 12,
                    "x": -0.0,
                    "y": 0.0,
                    "z": 0.0,
                    "confidence": 0.0
                },
                {
                    "pointID": 13,
                    "x": -0.0,
                    "y": 0.0,
                    "z": 0.0,
                    "confidence": 0.0
                },
                {
                    "pointID": 14,
                    "x": -0.0,
                    "y": 0.0,
                    "z": 0.0,
                    "confidence": 0.0
                },
                {
                    "pointID": 15,
                    "x": -0.020607588812708855,
                    "y": -0.6368038654327393,
                    "z": 1.3690000772476196,
                    "confidence": 0.8933131694793701
                },
                {
                    "pointID": 16,
                    "x": -0.0,
                    "y": 0.0,
                    "z": 0.0,
                    "confidence": 0.0
                },
                {
                    "pointID": 17,
                    "x": -0.05960068479180336,
                    "y": -0.6182605624198914,
                    "z": 1.4380000829696655,
                    "confidence": 0.7950867414474487
                },
                {
                    "pointID": 18,
                    "x": -0.0,
                    "y": 0.0,
                    "z": 0.0,
                    "confidence": 0.0
                },
                {
                    "pointID": 19,
                    "x": -0.0,
                    "y": 0.0,
                    "z": 0.0,
                    "confidence": 0.0
                },
                {
                    "pointID": 20,
                    "x": -0.0,
                    "y": 0.0,
                    "z": 0.0,
                    "confidence": 0.0
                },
                {
                    "pointID": 21,
                    "x": -0.0,
                    "y": 0.0,
                    "z": 0.0,
                    "confidence": 0.0
                },
                {
                    "pointID": 22,
                    "x": -0.0,
                    "y": 0.0,
                    "z": 0.0,
                    "confidence": 0.0
                },
                {
                    "pointID": 23,
                    "x": -0.0,
                    "y": 0.0,
                    "z": 0.0,
                    "confidence": 0.0
                },
                {
                    "pointID": 24,
                    "x": -0.0,
                    "y": 0.0,
                    "z": 0.0,
                    "confidence": 0.0
                }
            ]
        },
        {
            "face_rotation": {
                "pitch": 0.0,
                "yaw": 0.0,
                "roll": 0.0
            },
            "personID": 1,
            "skeleton": [
                {
                    "pointID": 0,
                    "x": 0.015588909387588501,
                    "y": -0.6535961031913757,
                    "z": 1.352000117301941,
                    "confidence": 0.8435017466545105
                },
                {
                    "pointID": 1,
                    "x": -0.008712617680430412,
                    "y": -0.75739985704422,
                    "z": 1.3890000581741333,
                    "confidence": 0.7884331345558167
                },
                {
                    "pointID": 2,
                    "x": -0.15824133157730103,
                    "y": -0.7239251136779785,
                    "z": 1.5250000953674316,
                    "confidence": 0.7918643355369568
                },
                {
                    "pointID": 3,
                    "x": -0.17962941527366638,
                    "y": -0.7516493797302246,
                    "z": 1.378000020980835,
                    "confidence": 0.2418212890625
                },
                {
                    "pointID": 4,
                    "x": -0.0,
                    "y": 0.0,
                    "z": 0.0,
                    "confidence": 0.0
                },
                {
                    "pointID": 5,
                    "x": 0.1555151343345642,
                    "y": -0.8495786786079407,
                    "z": 1.558000087738037,
                    "confidence": 0.5663161873817444
                },
                {
                    "pointID": 6,
                    "x": -0.0,
                    "y": 0.0,
                    "z": 0.0,
                    "confidence": 0.0
                },
                {
                    "pointID": 7,
                    "x": -0.0,
                    "y": 0.0,
                    "z": 0.0,
                    "confidence": 0.0
                },
                {
                    "pointID": 8,
                    "x": -0.0,
                    "y": 0.0,
                    "z": 0.0,
                    "confidence": 0.0
                },
                {
                    "pointID": 9,
                    "x": -0.0,
                    "y": 0.0,
                    "z": 0.0,
                    "confidence": 0.0
                },
                {
                    "pointID": 10,
                    "x": -0.0,
                    "y": 0.0,
                    "z": 0.0,
                    "confidence": 0.0
                },
                {
                    "pointID": 11,
                    "x": -0.0,
                    "y": 0.0,
                    "z": 0.0,
                    "confidence": 0.0
                },
                {
                    "pointID": 12,
                    "x": -0.0,
                    "y": 0.0,
                    "z": 0.0,
                    "confidence": 0.0
                },
                {
                    "pointID": 13,
                    "x": -0.0,
                    "y": 0.0,
                    "z": 0.0,
                    "confidence": 0.0
                },
                {
                    "pointID": 14,
                    "x": -0.0,
                    "y": 0.0,
                    "z": 0.0,
                    "confidence": 0.0
                },
                {
                    "pointID": 15,
                    "x": -0.0,
                    "y": 0.0,
                    "z": 0.0,
                    "confidence": 0.0
                },
                {
                    "pointID": 16,
                    "x": 0.0511309877038002,
                    "y": -0.6313860416412354,
                    "z": 1.3560000658035278,
                    "confidence": 0.9479433298110962
                },
                {
                    "pointID": 17,
                    "x": -0.0,
                    "y": 0.0,
                    "z": 0.0,
                    "confidence": 0.0
                },
                {
                    "pointID": 18,
                    "x": 0.1298452913761139,
                    "y": -0.6626303195953369,
                    "z": 1.4250000715255737,
                    "confidence": 0.882938027381897
                },
                {
                    "pointID": 19,
                    "x": -0.0,
                    "y": 0.0,
                    "z": 0.0,
                    "confidence": 0.0
                },
                {
                    "pointID": 20,
                    "x": -0.0,
                    "y": 0.0,
                    "z": 0.0,
                    "confidence": 0.0
                },
                {
                    "pointID": 21,
                    "x": -0.0,
                    "y": 0.0,
                    "z": 0.0,
                    "confidence": 0.0
                },
                {
                    "pointID": 22,
                    "x": -0.0,
                    "y": 0.0,
                    "z": 0.0,
                    "confidence": 0.0
                },
                {
                    "pointID": 23,
                    "x": -0.0,
                    "y": 0.0,
                    "z": 0.0,
                    "confidence": 0.0
                },
                {
                    "pointID": 24,
                    "x": -0.0,
                    "y": 0.0,
                    "z": 0.0,
                    "confidence": 0.0
                }
            ]
        }
    ],
    "thingId": "digitaltwin:Laboratorio_Corridoio:1",
    "Has_Fallen": false
}